infrascrap/__init__.py
infrascrap/config.py
infrascrap/exceptions.py
infrascrap/msging.py
infrascrap/utils.py
infrascrap-0.1.12.dist-info/WHEEL
infrascrap-0.1.12.dist-info/METADATA
infrascrap-0.1.12.dist-info/RECORD
